test/__init__.py
test/parser_test.py
wpscan_out_parse/__init__.py
wpscan_out_parse/__main__.py
wpscan_out_parse/__version__.py
wpscan_out_parse/formatter.py
wpscan_out_parse/parser/__init__.py
wpscan_out_parse/parser/_cli_parser.py
wpscan_out_parse/parser/_json_parser.py
wpscan_out_parse/parser/base.py
wpscan_out_parse/parser/results.py
wpscan_out_parse/parser/components/__init__.py
wpscan_out_parse/parser/components/_parts/__init__.py
wpscan_out_parse/parser/components/_parts/banner.py
wpscan_out_parse/parser/components/_parts/config_backup.py
wpscan_out_parse/parser/components/_parts/db_export.py
wpscan_out_parse/parser/components/_parts/finding.py
wpscan_out_parse/parser/components/_parts/interesting_finding.py
wpscan_out_parse/parser/components/_parts/main_theme.py
wpscan_out_parse/parser/components/_parts/media.py
wpscan_out_parse/parser/components/_parts/not_fully_configured.py
wpscan_out_parse/parser/components/_parts/password_attack.py
wpscan_out_parse/parser/components/_parts/plugin.py
wpscan_out_parse/parser/components/_parts/scan_finished.py
wpscan_out_parse/parser/components/_parts/scan_started.py
wpscan_out_parse/parser/components/_parts/theme.py
wpscan_out_parse/parser/components/_parts/timthumb.py
wpscan_out_parse/parser/components/_parts/user.py
wpscan_out_parse/parser/components/_parts/vuln_api.py
wpscan_out_parse/parser/components/_parts/wordpress_version.py
wpscan_out_parse/parser/components/_parts/wp_item.py
wpscan_out_parse/parser/components/_parts/wp_item_version.py
wpscan_out_parse-1.9.3.dist-info/LICENSE
wpscan_out_parse-1.9.3.dist-info/METADATA
wpscan_out_parse-1.9.3.dist-info/WHEEL
wpscan_out_parse-1.9.3.dist-info/entry_points.txt
wpscan_out_parse-1.9.3.dist-info/top_level.txt
wpscan_out_parse-1.9.3.dist-info/RECORD
