Metadata-Version: 2.1
Name: wpscan-out-parse
Version: 1.9.3
Summary: wpscan_out_parse is a Python parser for WPScan output files (JSON and CLI). It analyze vulnerabilities, miscellaneous alerts and warnings and other findings.
Home-page: http://github.com/tristanlatr/wpscan_out_parse
Maintainer: tristanlatr
License: MIT
Platform: UNKNOWN
Classifier: Programming Language :: Python :: 3
License-File: LICENSE
Requires-Dist: ansicolors
